zeppybot/__init__.py
zeppybot/py.typed
zeppybot-0.1.0.dist-info/METADATA
zeppybot-0.1.0.dist-info/WHEEL
zeppybot-0.1.0.dist-info/top_level.txt
zeppybot-0.1.0.dist-info/RECORD
