Metadata-Version: 2.4
Name: zeppybot
Version: 0.1.0
Summary: Threaded Selenium bot for Zeppy chat automation
Author-email: Deck <you@example.com>
License: All rights reserved.
Project-URL: Homepage, https://github.com/yourname/zeppybot
Project-URL: Source, https://github.com/yourname/zeppybot
Classifier: Programming Language :: Python
Classifier: Programming Language :: Python :: 3
Classifier: License :: Other/Proprietary License
Classifier: Operating System :: OS Independent
Requires-Python: >=3.9
Requires-Dist: selenium>=4.0
Requires-Dist: beautifulsoup4>=4.12
